mathenjeu/__init__.py
mathenjeu/__main__.py
mathenjeu/activities/__init__.py
mathenjeu/activities/act_question.py
mathenjeu/activities/base_classes.py
mathenjeu/apps/__init__.py
mathenjeu/apps/common/__init__.py
mathenjeu/apps/common/auth_app.py
mathenjeu/apps/common/log_app.py
mathenjeu/apps/display/__init__.py
mathenjeu/apps/display/html_display.py
mathenjeu/apps/qcm/__init__.py
mathenjeu/apps/qcm/qcm_app.py
mathenjeu/apps/qcm/statics/__init__.py
mathenjeu/apps/qcm/statics/css/__init__.py
mathenjeu/apps/qcm/statics/css/bootstrap.min.css
mathenjeu/apps/qcm/statics/css/custom.css
mathenjeu/apps/qcm/statics/img/__init__.py
mathenjeu/apps/qcm/statics/img/coeur.png
mathenjeu/apps/qcm/statics/img/koch.png
mathenjeu/apps/qcm/statics/img/pen.png
mathenjeu/apps/qcm/statics/js/__init__.py
mathenjeu/apps/qcm/statics/js/bootstrap.min.js
mathenjeu/apps/qcm/statics/js/jquery-3.3.1.slim.min.js
mathenjeu/apps/qcm/statics/js/popper.min.js
mathenjeu/apps/qcm/templates/404.html
mathenjeu/apps/qcm/templates/500.html
mathenjeu/apps/qcm/templates/__init__.py
mathenjeu/apps/qcm/templates/authorized.html
mathenjeu/apps/qcm/templates/base.html
mathenjeu/apps/qcm/templates/index.html
mathenjeu/apps/qcm/templates/lastpage.html
mathenjeu/apps/qcm/templates/login.html
mathenjeu/apps/qcm/templates/nogame.html
mathenjeu/apps/qcm/templates/notauthorized.html
mathenjeu/apps/qcm/templates/notlogged.html
mathenjeu/apps/qcm/templates/qcm.html
mathenjeu/apps/server/__init__.py
mathenjeu/apps/server/server_hypercorn.py
mathenjeu/apps/staticapp/__init__.py
mathenjeu/apps/staticapp/authmount.py
mathenjeu/apps/staticapp/staticsite.py
mathenjeu/apps/staticapp/statics/__init__.py
mathenjeu/apps/staticapp/statics/css/__init__.py
mathenjeu/apps/staticapp/statics/css/bootstrap.min.css
mathenjeu/apps/staticapp/statics/css/custom.css
mathenjeu/apps/staticapp/statics/img/__init__.py
mathenjeu/apps/staticapp/statics/img/coeur.png
mathenjeu/apps/staticapp/statics/img/koch.png
mathenjeu-0.2.114.dist-info/LICENSE.txt
mathenjeu-0.2.114.dist-info/METADATA
mathenjeu-0.2.114.dist-info/WHEEL
mathenjeu-0.2.114.dist-info/top_level.txt
mathenjeu-0.2.114.dist-info/RECORD
