Metadata-Version: 2.1
Name: mathenjeu
Version: 0.2.114
Summary: Lectures about programming mostly in Python.
Home-page: http://www.xavierdupre.fr/app/mathenjeu/helpsphinx/index.html
Author: Xavier Dupré
Author-email: xavier.dupre@gmail.com
License: MIT
Download-URL: https://github.com/sdpython/mathenjeu/
Keywords: mathenjeu,Xavier Dupré
Platform: UNKNOWN
Classifier: Programming Language :: Python :: 3
Classifier: Intended Audience :: Developers
Classifier: Topic :: Scientific/Engineering
Classifier: Topic :: Education
Classifier: License :: OSI Approved :: MIT License
Classifier: Development Status :: 5 - Production/Stable
Requires-Dist: aiofiles
Requires-Dist: itsdangerous
Requires-Dist: jinja2
Requires-Dist: lightmlrestapi
Requires-Dist: numpy
Requires-Dist: pandas
Requires-Dist: python-multipart
Requires-Dist: starlette (>=0.11.0)
Requires-Dist: hypercorn
Requires-Dist: pyopenssl
